tree_swarm/__init__.py
tree_swarm/actions/__init__.py
tree_swarm/actions/action_space_metadata.json
tree_swarm/actions/action_space_metadata.sqlite3
tree_swarm/actions/communication/talk_to_user.py
tree_swarm/actions/reasoning/__init__.py
tree_swarm/actions/reasoning/decompose_directive.py
tree_swarm/actions/reasoning/route_goal.py
tree_swarm/memory/__init__.py
tree_swarm/memory/memory_space_metadata.json
tree_swarm/memory/swarm/__init__.py
tree_swarm/memory/swarm/documentation/__init__.py
tree_swarm/memory/swarm/documentation/configuration_chatbot.md
tree_swarm/swarm/__init__.py
tree_swarm/swarm/swarm_master.py
tree_swarm/swarm/swarm_setup.py
tree_swarm/swarm/types/__init__.py
tree_swarm/swarm/types/action_metadata.py
tree_swarm/swarm/types/memory_metadata.py
tree_swarm/swarm/types/swarm.py
tree_swarm/swarm/types/swarm_history.py
tree_swarm/swarm/types/swarm_lifecycle.py
tree_swarm/swarm/types/swarm_state.py
tree_swarm/swarm/types/util_metadata.py
tree_swarm/utils/__init__.py
tree_swarm/utils/action_utils/__init__.py
tree_swarm/utils/action_utils/execute_action/__init__.py
tree_swarm/utils/action_utils/execute_action/internal_python_main.py
tree_swarm/utils/action_utils/execute_action/main.py
tree_swarm/utils/action_utils/execute_blocking_operation/__init__.py
tree_swarm/utils/action_utils/execute_blocking_operation/internal_action.py
tree_swarm/utils/action_utils/execute_blocking_operation/main.py
tree_swarm/utils/action_utils/execute_blocking_operation/openai_instructor_completion.py
tree_swarm/utils/ai/openai_instructor.py
tree_swarm/utils/data/__init__.py
tree_swarm/utils/data/file_operations/__init__.py
tree_swarm/utils/data/file_operations/azure_blob_storage.py
tree_swarm/utils/data/file_operations/local_storage.py
tree_swarm/utils/data/file_operations/main.py
tree_swarm/utils/data/folder_operations/__init__.py
tree_swarm/utils/data/folder_operations/azure_blob_storage.py
tree_swarm/utils/data/folder_operations/local_storage.py
tree_swarm-0.1.0.dist-info/LICENSE
tree_swarm-0.1.0.dist-info/METADATA
tree_swarm-0.1.0.dist-info/WHEEL
tree_swarm-0.1.0.dist-info/RECORD
